irrd/__init__.py
irrd/conf/__init__.py
irrd/conf/default_config.yaml
irrd/conf/defaults.py
irrd/conf/known_keys.py
irrd/conf/test_conf.py
irrd/daemon/__init__.py
irrd/daemon/main.py
irrd/mirroring/__init__.py
irrd/mirroring/jobs.py
irrd/mirroring/mirror_runners_export.py
irrd/mirroring/mirror_runners_import.py
irrd/mirroring/nrtm4/__init__.py
irrd/mirroring/nrtm4/jsonseq.py
irrd/mirroring/nrtm4/nrtm4_client.py
irrd/mirroring/nrtm4/nrtm4_server.py
irrd/mirroring/nrtm4/nrtm4_types.py
irrd/mirroring/nrtm_generator.py
irrd/mirroring/nrtm_operation.py
irrd/mirroring/parsers.py
irrd/mirroring/retrieval.py
irrd/mirroring/scheduler.py
irrd/routepref/__init__.py
irrd/routepref/routepref.py
irrd/routepref/status.py
irrd/rpki/__init__.py
irrd/rpki/importer.py
irrd/rpki/notifications.py
irrd/rpki/status.py
irrd/rpki/validators.py
irrd/rpsl/__init__.py
irrd/rpsl/auth.py
irrd/rpsl/fields.py
irrd/rpsl/parser.py
irrd/rpsl/parser_state.py
irrd/rpsl/rpsl_objects.py
irrd/scopefilter/__init__.py
irrd/scopefilter/status.py
irrd/scopefilter/validators.py
irrd/scripts/__init__.py
irrd/scripts/database_downgrade.py
irrd/scripts/database_upgrade.py
irrd/scripts/expire_journal.py
irrd/scripts/irr_rpsl_submit.py
irrd/scripts/irrd_control.py
irrd/scripts/load_database.py
irrd/scripts/load_pgp_keys.py
irrd/scripts/load_test.py
irrd/scripts/mirror_force_reload.py
irrd/scripts/query_qa_comparison.py
irrd/scripts/rpsl_read.py
irrd/scripts/set_last_modified_auth.py
irrd/scripts/submit_changes.py
irrd/scripts/submit_email.py
irrd/scripts/update_database.py
irrd/server/__init__.py
irrd/server/access_check.py
irrd/server/graphql/__init__.py
irrd/server/graphql/extensions.py
irrd/server/graphql/resolvers.py
irrd/server/graphql/schema_builder.py
irrd/server/graphql/schema_generator.py
irrd/server/http/__init__.py
irrd/server/http/app.py
irrd/server/http/endpoints_api.py
irrd/server/http/event_stream.py
irrd/server/http/metrics_generator.py
irrd/server/http/server.py
irrd/server/http/status_generator.py
irrd-4.5.0.dist-info/LICENSE
irrd-4.5.0.dist-info/METADATA
irrd-4.5.0.dist-info/WHEEL
irrd-4.5.0.dist-info/entry_points.txt
irrd-4.5.0.dist-info/RECORD
