Metadata-Version: 2.3
Name: irrd
Version: 4.5.0
Summary: Internet Routing Registry daemon (IRRd)
License: BSD
Author: Reliably Coded for NTT Ltd. and others
Author-email: irrd@reliablycoded.nl
Requires-Python: >3.10.0,<4.0
Classifier: License :: Other/Proprietary License
Classifier: Programming Language :: Python :: 3
Classifier: Programming Language :: Python :: 3.11
Classifier: Programming Language :: Python :: 3.12
Classifier: Programming Language :: Python :: 3.13
Requires-Dist: alembic (==1.18.1)
Requires-Dist: ariadne (==0.27.0)
Requires-Dist: asgi-logger (==0.1.0)
Requires-Dist: asgiref (==3.11.0)
Requires-Dist: bcrypt (==4.3.0)
Requires-Dist: beautifultable (==0.8.0)
Requires-Dist: click (==8.3.1)
Requires-Dist: coredis (==5.4.0)
Requires-Dist: datrie (==0.8.3)
Requires-Dist: email-validator (==2.3.0)
Requires-Dist: hiredis (==3.3.0)
Requires-Dist: imia (==0.5.3)
Requires-Dist: ipy (==1.1)
Requires-Dist: jinja2 (==3.1.6)
Requires-Dist: joserfc (==1.6.1)
Requires-Dist: limits (==5.6.0)
Requires-Dist: ordered-set (==4.1.0)
Requires-Dist: passlib (==1.7.4)
Requires-Dist: pid (==3.0.4)
Requires-Dist: psutil (==7.2.1)
Requires-Dist: psycopg2-binary (==2.9.11)
Requires-Dist: py-radix-sr (==1.0.2)
Requires-Dist: pydantic (==2.12.5)
Requires-Dist: pyotp (==2.9.0)
Requires-Dist: python-daemon (==3.1.2)
Requires-Dist: python-gnupg (==0.5.6)
Requires-Dist: python-multipart (==0.0.22)
Requires-Dist: pytz (==2025.2)
Requires-Dist: pyyaml (==6.0.3)
Requires-Dist: redis (==7.1.0)
Requires-Dist: requests (==2.32.5)
Requires-Dist: setproctitle (==1.3.7)
Requires-Dist: sqlalchemy (==1.4.54)
Requires-Dist: starlette (==0.52.1)
Requires-Dist: starlette-wtf (==0.4.5)
Requires-Dist: time-machine (==3.2.0)
Requires-Dist: typing-extensions (==4.15.0)
Requires-Dist: ujson (==5.11.0)
Requires-Dist: uvicorn[standard] (==0.40.0)
Requires-Dist: webauthn (==2.7.0)
Requires-Dist: wheel (==0.46.2)
Requires-Dist: wtforms-bootstrap5 (==0.3.0)
Requires-Dist: zxcvbn (==4.5.0)
Project-URL: Documentation, https://irrd.readthedocs.io/
Project-URL: Repository, https://github.com/irrdnet/irrd
